{
  "appInfo" : {
    "build" : "232.9881.19.143",
    "buildDate" : "2023-09-02T05:11:46.322Z[UTC]",
    "productCode" : "QDNET",
    "generated" : "2023-09-26T06:28:11.242862872Z",
    "os" : "Linux 6.2.0-1011-azure",
    "runtime" : "JetBrains s.r.o. 17.0.8 17.0.8+7-b1000.8"
  },
  "runtimeInfo" : {
    "maxMemory" : 5083496448,
    "numberOfProcessors" : 2,
    "maxNumberOfIndexingThreads" : 2,
    "maxSizeOfFileForIntelliSense" : 2560000,
    "maxSizeOfFileForContentLoading" : 20971520
  },
  "type" : "DumbIndexing",
  "projectIndexingActivityHistory" : {
    "projectName" : "project",
    "times" : {
      "scanningIds" : [ 0 ],
      "contentLoadingVisibleTime" : 1652161173,
      "retrievingChangedDuringIndexingFilesTime" : 13720173,
      "isAppliedAllValuesSeparately" : true,
      "separateApplyingIndexesVisibleTime" : 732451147,
      "updatingStart" : "2023-09-26T06:28:06.90737811Z",
      "updatingEnd" : "2023-09-26T06:28:11.234352627Z",
      "totalWallTimeWithPauses" : 4326963817,
      "wallTimeOnPause" : 0,
      "wasInterrupted" : false,
      "dumbModeStart" : "2023-09-26T06:28:06.90737811Z",
      "dumbWallTimeWithPauses" : 4326963817,
      "dumbWallTimeWithoutPauses" : 4326963817,
      "totalWallTimeWithoutPauses" : 4326963817
    },
    "fileCount" : {
      "numberOfChangedDuringIndexingFiles" : 1254,
      "numberOfFilesIndexedByInfrastructureExtensionsDuringIndexingStage" : 0,
      "numberOfFilesIndexedWithLoadingContent" : 1255
    },
    "totalStatsPerFileType" : [ {
      "fileType" : "UnityYaml",
      "partOfTotalProcessingTime" : {
        "part" : 5395373098,
        "total" : 8114923369
      },
      "partOfTotalContentLoadingTime" : {
        "part" : 2555818907,
        "total" : 3230268005
      },
      "totalNumberOfFiles" : 796,
      "totalFilesSize" : 9488180,
      "totalProcessingSpeed" : {
        "totalBytes" : 9488180,
        "totalCpuTime" : 5395373098
      },
      "biggestContributors" : [ {
        "providerName" : "Refreshed files",
        "numberOfFiles" : 796,
        "totalFilesSize" : 9488180,
        "partOfTotalProcessingTimeOfThisFileType" : {
          "part" : 5395373098,
          "total" : 5395373098
        }
      } ]
    }, {
      "fileType" : "C#",
      "partOfTotalProcessingTime" : {
        "part" : 1100484661,
        "total" : 8114923369
      },
      "partOfTotalContentLoadingTime" : {
        "part" : 477210347,
        "total" : 3230268005
      },
      "totalNumberOfFiles" : 295,
      "totalFilesSize" : 2835714,
      "totalProcessingSpeed" : {
        "totalBytes" : 2835714,
        "totalCpuTime" : 1100484661
      },
      "biggestContributors" : [ {
        "providerName" : "Refreshed files",
        "numberOfFiles" : 295,
        "totalFilesSize" : 2835714,
        "partOfTotalProcessingTimeOfThisFileType" : {
          "part" : 1100484661,
          "total" : 1100484661
        }
      } ]
    }, {
      "fileType" : "PLAIN_TEXT",
      "partOfTotalProcessingTime" : {
        "part" : 930968549,
        "total" : 8114923369
      },
      "partOfTotalContentLoadingTime" : {
        "part" : 73373388,
        "total" : 3230268005
      },
      "totalNumberOfFiles" : 104,
      "totalFilesSize" : 3043098,
      "totalProcessingSpeed" : {
        "totalBytes" : 3043098,
        "totalCpuTime" : 930968549
      },
      "biggestContributors" : [ {
        "providerName" : "Refreshed files",
        "numberOfFiles" : 104,
        "totalFilesSize" : 3043098,
        "partOfTotalProcessingTimeOfThisFileType" : {
          "part" : 930968549,
          "total" : 930968549
        }
      } ]
    }, {
      "fileType" : "XML",
      "partOfTotalProcessingTime" : {
        "part" : 260244684,
        "total" : 8114923369
      },
      "partOfTotalContentLoadingTime" : {
        "part" : 8530346,
        "total" : 3230268005
      },
      "totalNumberOfFiles" : 1,
      "totalFilesSize" : 1748,
      "totalProcessingSpeed" : {
        "totalBytes" : 1748,
        "totalCpuTime" : 260244684
      },
      "biggestContributors" : [ {
        "providerName" : "Indexable set contributor 'com.intellij.javaee.ExternalResourcesRootsProvider@4a072d08' (non-project)",
        "numberOfFiles" : 1,
        "totalFilesSize" : 1748,
        "partOfTotalProcessingTimeOfThisFileType" : {
          "part" : 260244684,
          "total" : 260244684
        }
      } ]
    }, {
      "fileType" : "YAML",
      "partOfTotalProcessingTime" : {
        "part" : 219840870,
        "total" : 8114923369
      },
      "partOfTotalContentLoadingTime" : {
        "part" : 464502,
        "total" : 3230268005
      },
      "totalNumberOfFiles" : 1,
      "totalFilesSize" : 295,
      "totalProcessingSpeed" : {
        "totalBytes" : 295,
        "totalCpuTime" : 219840870
      },
      "biggestContributors" : [ {
        "providerName" : "Refreshed files",
        "numberOfFiles" : 1,
        "totalFilesSize" : 295,
        "partOfTotalProcessingTimeOfThisFileType" : {
          "part" : 219840870,
          "total" : 219840870
        }
      } ]
    }, {
      "fileType" : "AsmDef",
      "partOfTotalProcessingTime" : {
        "part" : 92530891,
        "total" : 8114923369
      },
      "partOfTotalContentLoadingTime" : {
        "part" : 51643174,
        "total" : 3230268005
      },
      "totalNumberOfFiles" : 24,
      "totalFilesSize" : 14012,
      "totalProcessingSpeed" : {
        "totalBytes" : 14012,
        "totalCpuTime" : 92530891
      },
      "biggestContributors" : [ {
        "providerName" : "Refreshed files",
        "numberOfFiles" : 24,
        "totalFilesSize" : 14012,
        "partOfTotalProcessingTimeOfThisFileType" : {
          "part" : 92530891,
          "total" : 92530891
        }
      } ]
    }, {
      "fileType" : "JSON",
      "partOfTotalProcessingTime" : {
        "part" : 50408368,
        "total" : 8114923369
      },
      "partOfTotalContentLoadingTime" : {
        "part" : 25697039,
        "total" : 3230268005
      },
      "totalNumberOfFiles" : 13,
      "totalFilesSize" : 30288,
      "totalProcessingSpeed" : {
        "totalBytes" : 30288,
        "totalCpuTime" : 50408368
      },
      "biggestContributors" : [ {
        "providerName" : "Refreshed files",
        "numberOfFiles" : 13,
        "totalFilesSize" : 30288,
        "partOfTotalProcessingTimeOfThisFileType" : {
          "part" : 50408368,
          "total" : 50408368
        }
      } ]
    }, {
      "fileType" : "ShaderLab",
      "partOfTotalProcessingTime" : {
        "part" : 48708961,
        "total" : 8114923369
      },
      "partOfTotalContentLoadingTime" : {
        "part" : 29587558,
        "total" : 3230268005
      },
      "totalNumberOfFiles" : 14,
      "totalFilesSize" : 82696,
      "totalProcessingSpeed" : {
        "totalBytes" : 82696,
        "totalCpuTime" : 48708961
      },
      "biggestContributors" : [ {
        "providerName" : "Refreshed files",
        "numberOfFiles" : 14,
        "totalFilesSize" : 82696,
        "partOfTotalProcessingTimeOfThisFileType" : {
          "part" : 48708961,
          "total" : 48708961
        }
      } ]
    }, {
      "fileType" : "HLSL",
      "partOfTotalProcessingTime" : {
        "part" : 10138054,
        "total" : 8114923369
      },
      "partOfTotalContentLoadingTime" : {
        "part" : 6922838,
        "total" : 3230268005
      },
      "totalNumberOfFiles" : 4,
      "totalFilesSize" : 13994,
      "totalProcessingSpeed" : {
        "totalBytes" : 13994,
        "totalCpuTime" : 10138054
      },
      "biggestContributors" : [ {
        "providerName" : "Refreshed files",
        "numberOfFiles" : 4,
        "totalFilesSize" : 13994,
        "partOfTotalProcessingTimeOfThisFileType" : {
          "part" : 10138054,
          "total" : 10138054
        }
      } ]
    }, {
      "fileType" : "InputActions",
      "partOfTotalProcessingTime" : {
        "part" : 4109222,
        "total" : 8114923369
      },
      "partOfTotalContentLoadingTime" : {
        "part" : 605604,
        "total" : 3230268005
      },
      "totalNumberOfFiles" : 1,
      "totalFilesSize" : 11942,
      "totalProcessingSpeed" : {
        "totalBytes" : 11942,
        "totalCpuTime" : 4109222
      },
      "biggestContributors" : [ {
        "providerName" : "Refreshed files",
        "numberOfFiles" : 1,
        "totalFilesSize" : 11942,
        "partOfTotalProcessingTimeOfThisFileType" : {
          "part" : 4109222,
          "total" : 4109222
        }
      } ]
    }, {
      "fileType" : "UNKNOWN",
      "partOfTotalProcessingTime" : {
        "part" : 1473508,
        "total" : 8114923369
      },
      "partOfTotalContentLoadingTime" : {
        "part" : 283401,
        "total" : 3230268005
      },
      "totalNumberOfFiles" : 1,
      "totalFilesSize" : 0,
      "totalProcessingSpeed" : {
        "totalBytes" : 0,
        "totalCpuTime" : 1473508
      },
      "biggestContributors" : [ {
        "providerName" : "Refreshed files",
        "numberOfFiles" : 1,
        "totalFilesSize" : 0,
        "partOfTotalProcessingTimeOfThisFileType" : {
          "part" : 1473508,
          "total" : 1473508
        }
      } ]
    }, {
      "fileType" : "Config",
      "partOfTotalProcessingTime" : {
        "part" : 642503,
        "total" : 8114923369
      },
      "partOfTotalContentLoadingTime" : {
        "part" : 130901,
        "total" : 3230268005
      },
      "totalNumberOfFiles" : 1,
      "totalFilesSize" : 0,
      "totalProcessingSpeed" : {
        "totalBytes" : 0,
        "totalCpuTime" : 642503
      },
      "biggestContributors" : [ {
        "providerName" : "Refreshed files",
        "numberOfFiles" : 1,
        "totalFilesSize" : 0,
        "partOfTotalProcessingTimeOfThisFileType" : {
          "part" : 642503,
          "total" : 642503
        }
      } ]
    } ],
    "totalStatsPerBaseLanguage" : [ {
      "language" : "UnityYaml",
      "partOfTotalProcessingTime" : {
        "part" : 5395373098,
        "total" : 8114923369
      },
      "partOfTotalContentLoadingTime" : {
        "part" : 5786086912,
        "total" : 3230268005
      },
      "totalNumberOfFiles" : 796,
      "totalFilesSize" : 9488180,
      "totalProcessingSpeed" : {
        "totalBytes" : 9488180,
        "totalCpuTime" : 5395373098
      }
    }, {
      "language" : "C#",
      "partOfTotalProcessingTime" : {
        "part" : 1100484661,
        "total" : 8114923369
      },
      "partOfTotalContentLoadingTime" : {
        "part" : 3707478352,
        "total" : 3230268005
      },
      "totalNumberOfFiles" : 295,
      "totalFilesSize" : 2835714,
      "totalProcessingSpeed" : {
        "totalBytes" : 2835714,
        "totalCpuTime" : 1100484661
      }
    }, {
      "language" : "TEXT",
      "partOfTotalProcessingTime" : {
        "part" : 930968549,
        "total" : 8114923369
      },
      "partOfTotalContentLoadingTime" : {
        "part" : 3303641393,
        "total" : 3230268005
      },
      "totalNumberOfFiles" : 104,
      "totalFilesSize" : 3043098,
      "totalProcessingSpeed" : {
        "totalBytes" : 3043098,
        "totalCpuTime" : 930968549
      }
    }, {
      "language" : "XML",
      "partOfTotalProcessingTime" : {
        "part" : 260887187,
        "total" : 8114923369
      },
      "partOfTotalContentLoadingTime" : {
        "part" : 3230398906,
        "total" : 3230268005
      },
      "totalNumberOfFiles" : 2,
      "totalFilesSize" : 1748,
      "totalProcessingSpeed" : {
        "totalBytes" : 1748,
        "totalCpuTime" : 260887187
      }
    }, {
      "language" : "yaml",
      "partOfTotalProcessingTime" : {
        "part" : 219840870,
        "total" : 8114923369
      },
      "partOfTotalContentLoadingTime" : {
        "part" : 3230732507,
        "total" : 3230268005
      },
      "totalNumberOfFiles" : 1,
      "totalFilesSize" : 295,
      "totalProcessingSpeed" : {
        "totalBytes" : 295,
        "totalCpuTime" : 219840870
      }
    }, {
      "language" : "JSON",
      "partOfTotalProcessingTime" : {
        "part" : 147048481,
        "total" : 8114923369
      },
      "partOfTotalContentLoadingTime" : {
        "part" : 3255965044,
        "total" : 3230268005
      },
      "totalNumberOfFiles" : 38,
      "totalFilesSize" : 56242,
      "totalProcessingSpeed" : {
        "totalBytes" : 56242,
        "totalCpuTime" : 147048481
      }
    }, {
      "language" : "ShaderLab",
      "partOfTotalProcessingTime" : {
        "part" : 48708961,
        "total" : 8114923369
      },
      "partOfTotalContentLoadingTime" : {
        "part" : 3259855563,
        "total" : 3230268005
      },
      "totalNumberOfFiles" : 14,
      "totalFilesSize" : 82696,
      "totalProcessingSpeed" : {
        "totalBytes" : 82696,
        "totalCpuTime" : 48708961
      }
    }, {
      "language" : "C++",
      "partOfTotalProcessingTime" : {
        "part" : 10138054,
        "total" : 8114923369
      },
      "partOfTotalContentLoadingTime" : {
        "part" : 3237190843,
        "total" : 3230268005
      },
      "totalNumberOfFiles" : 4,
      "totalFilesSize" : 13994,
      "totalProcessingSpeed" : {
        "totalBytes" : 13994,
        "totalCpuTime" : 10138054
      }
    }, {
      "language" : "Config",
      "partOfTotalProcessingTime" : {
        "part" : 642503,
        "total" : 8114923369
      },
      "partOfTotalContentLoadingTime" : {
        "part" : 3230398906,
        "total" : 3230268005
      },
      "totalNumberOfFiles" : 1,
      "totalFilesSize" : 0,
      "totalProcessingSpeed" : {
        "totalBytes" : 0,
        "totalCpuTime" : 642503
      }
    } ],
    "totalStatsPerIndexer" : [ {
      "indexId" : "IdIndex",
      "partOfTotalIndexingTime" : {
        "part" : 1565330245,
        "total" : 2843101447
      },
      "totalNumberOfFiles" : 1254,
      "totalNumberOfFilesIndexedByExtensions" : 0,
      "totalFilesSize" : 15521967,
      "indexValueChangerEvaluationSpeed" : {
        "totalBytes" : 15521967,
        "totalCpuTime" : 1565330245
      },
      "snapshotInputMappingStats" : {
        "totalRequests" : 0,
        "totalMisses" : 0,
        "totalHits" : 0
      }
    }, {
      "indexId" : "Trigram.Index",
      "partOfTotalIndexingTime" : {
        "part" : 924352218,
        "total" : 2843101447
      },
      "totalNumberOfFiles" : 1254,
      "totalNumberOfFilesIndexedByExtensions" : 0,
      "totalFilesSize" : 15521967,
      "indexValueChangerEvaluationSpeed" : {
        "totalBytes" : 15521967,
        "totalCpuTime" : 924352218
      },
      "snapshotInputMappingStats" : {
        "totalRequests" : 0,
        "totalMisses" : 0,
        "totalHits" : 0
      }
    }, {
      "indexId" : "yaml.keys.name",
      "partOfTotalIndexingTime" : {
        "part" : 214712744,
        "total" : 2843101447
      },
      "totalNumberOfFiles" : 1,
      "totalNumberOfFilesIndexedByExtensions" : 0,
      "totalFilesSize" : 295,
      "indexValueChangerEvaluationSpeed" : {
        "totalBytes" : 295,
        "totalCpuTime" : 214712744
      },
      "snapshotInputMappingStats" : {
        "totalRequests" : 0,
        "totalMisses" : 0,
        "totalHits" : 0
      }
    }, {
      "indexId" : "DomFileIndex",
      "partOfTotalIndexingTime" : {
        "part" : 65641549,
        "total" : 2843101447
      },
      "totalNumberOfFiles" : 1,
      "totalNumberOfFilesIndexedByExtensions" : 0,
      "totalFilesSize" : 1748,
      "indexValueChangerEvaluationSpeed" : {
        "totalBytes" : 1748,
        "totalCpuTime" : 65641549
      },
      "snapshotInputMappingStats" : {
        "totalRequests" : 0,
        "totalMisses" : 0,
        "totalHits" : 0
      }
    }, {
      "indexId" : "Stubs",
      "partOfTotalIndexingTime" : {
        "part" : 60939224,
        "total" : 2843101447
      },
      "totalNumberOfFiles" : 1,
      "totalNumberOfFilesIndexedByExtensions" : 0,
      "totalFilesSize" : 1748,
      "indexValueChangerEvaluationSpeed" : {
        "totalBytes" : 1748,
        "totalCpuTime" : 60939224
      },
      "snapshotInputMappingStats" : {
        "totalRequests" : 0,
        "totalMisses" : 0,
        "totalHits" : 0
      }
    }, {
      "indexId" : "json.file.root.values",
      "partOfTotalIndexingTime" : {
        "part" : 8894149,
        "total" : 2843101447
      },
      "totalNumberOfFiles" : 38,
      "totalNumberOfFilesIndexedByExtensions" : 0,
      "totalFilesSize" : 56242,
      "indexValueChangerEvaluationSpeed" : {
        "totalBytes" : 56242,
        "totalCpuTime" : 8894149
      },
      "snapshotInputMappingStats" : {
        "totalRequests" : 0,
        "totalMisses" : 0,
        "totalHits" : 0
      }
    }, {
      "indexId" : "XmlNamespaces",
      "partOfTotalIndexingTime" : {
        "part" : 3231318,
        "total" : 2843101447
      },
      "totalNumberOfFiles" : 1,
      "totalNumberOfFilesIndexedByExtensions" : 0,
      "totalFilesSize" : 1748,
      "indexValueChangerEvaluationSpeed" : {
        "totalBytes" : 1748,
        "totalCpuTime" : 3231318
      },
      "snapshotInputMappingStats" : {
        "totalRequests" : 0,
        "totalMisses" : 0,
        "totalHits" : 0
      }
    } ],
    "statisticsOfChangedDuringIndexingFiles" : {
      "numberOfFiles" : 1254,
      "retrievingTime" : 13720173
    },
    "fileProviderStatistics" : [ {
      "providerName" : "Refreshed files",
      "totalNumberOfIndexedFiles" : 1254,
      "totalNumberOfFilesFullyIndexedByExtensions" : 0,
      "totalIndexingVisibleTime" : 4006562413,
      "contentLoadingVisibleTime" : 1643363595,
      "numberOfTooLargeForIndexingFiles" : 0,
      "slowIndexedFiles" : [ ],
      "filesFullyIndexedByExtensions" : [ ],
      "isAppliedAllValuesSeparately" : true,
      "separateApplyingIndexesVisibleTime" : 650655222
    }, {
      "providerName" : "Indexable set contributor 'com.intellij.javaee.ExternalResourcesRootsProvider@4a072d08' (non-project)",
      "totalNumberOfIndexedFiles" : 1,
      "totalNumberOfFilesFullyIndexedByExtensions" : 0,
      "totalIndexingVisibleTime" : 268397425,
      "contentLoadingVisibleTime" : 8797578,
      "numberOfTooLargeForIndexingFiles" : 0,
      "slowIndexedFiles" : [ ],
      "filesFullyIndexedByExtensions" : [ ],
      "isAppliedAllValuesSeparately" : true,
      "separateApplyingIndexesVisibleTime" : 81795925
    } ],
    "visibleTimeToAllThreadTimeRatio" : 0.5100860994672247
  }
}